locloc/__init__.py
locloc/loc.py
locloc/main.py
locloc/py.typed
locloc/static_files/favicon.ico
locloc/static_files/favicon.png
locloc/static_files/index.css
locloc/static_files/index.js
locloc/templates/index.j2
locloc-0.1.1.dist-info/METADATA
locloc-0.1.1.dist-info/WHEEL
locloc-0.1.1.dist-info/entry_points.txt
locloc-0.1.1.dist-info/licenses/LICENSE.txt
locloc-0.1.1.dist-info/RECORD
