Metadata-Version: 2.4
Name: locloc
Version: 0.1.1
Summary: Online LOC counter
Project-URL: Repository, https://github.com/eggplants/locloc
Author-email: eggplants <w10776e8w@yahoo.co.jp>
License: MIT
License-File: LICENSE.txt
Keywords: loc,web
Classifier: License :: OSI Approved :: MIT License
Classifier: Programming Language :: Python
Classifier: Programming Language :: Python :: 3 :: Only
Classifier: Programming Language :: Python :: 3.13
Classifier: Programming Language :: Python :: 3.14
Classifier: Programming Language :: Python :: Implementation :: CPython
Classifier: Typing :: Typed
Requires-Python: <4,>=3.13
Requires-Dist: fastapi<0.129,>=0.115.6
Requires-Dist: gitpython<4,>=3.1.44
Requires-Dist: jinja2<4,>=3.1.5
Requires-Dist: pydantic<3,>=2.10.5
Requires-Dist: pygal<4,>=3.0.5
Requires-Dist: pytokei<0.3,>=0.2
Requires-Dist: timeout-decorator<0.6,>=0.5
Requires-Dist: uvicorn<0.41,>=0.34
